LICENSE
README.md
setup.py
mdbrtools/__init__.py
mdbrtools/common.py
mdbrtools/estimator.py
mdbrtools/mongodb.py
mdbrtools/query.py
mdbrtools/schema.py
mdbrtools/workload.py
mdbrtools.egg-info/PKG-INFO
mdbrtools.egg-info/SOURCES.txt
mdbrtools.egg-info/dependency_links.txt
mdbrtools.egg-info/not-zip-safe
mdbrtools.egg-info/requires.txt
mdbrtools.egg-info/top_level.txt
tests/__init__.py
tests/test_common.py
tests/test_query.py
tests/test_schema.py
tests/test_workload.py