Metadata-Version: 2.1
Name: mdbrtools
Version: 0.1.0
Summary: Collection of tools for schema parsing and workload generation used by MongoDB Research
Home-page: http://github.com/mongodb-labs/mdbrtools
Author: Thomas Rueckstiess, Alana Huang, Robin Vujanic
Author-email: thomas+mdbrtools@mongodb.com
License: MIT
Keywords: mongodb research tools schema queries workload
License-File: LICENSE
